{ 
  "assets": [
    {
      "id":1,
      "logo":"/dashboard/company_logo/algem_logo.svg",
      "pageLink":"https://www.algem.io/",
      "name": "Algem",
      "trusted": true,
      "audit": {
        "link": "https://github.com/Defimoonorg/Audit-Report/blob/main/Algem_SiriusHandler_reAuditReport.pdf"
      },
      "ecosystem": {
        "name": "astar",
        "icon": "/dashboard/chains/astar_chain.svg"
      },
      "category": "DeFi",
      "issues": {
        "high": 0,
        "medium": 0,
        "low": 0,
        "informational": 1
      }
    },
    {
      "id": 2,
      "logo": "/dashboard/company_logo/na_logo.svg",
      "pageLink":false,
      "name": "Artpad",
      "trusted":false,
      "audit": {
        "link": "https://github.com/Defimoonorg/Audit-Report/blob/main/Artpad_audit.pdf"
      },
      "ecosystem": {
        "name":"solana",
        "icon":""
      },
      "category":"DeFi",
      "issues": {
        "high": 1,
        "medium": 1,
        "low": 1,
        "informational": 0
      }
    },
    {
      "id": 3,
      "logo": "/dashboard/company_logo/na_logo.svg",
      "pageLink":false,
      "name": "Artpad",
      "trusted":false,
      "audit": {
        "link": "https://github.com/Defimoonorg/Audit-Report/blob/main/Artpad_audit.pdf"
      },
      "ecosystem": {
        "name":"solana",
        "icon":""
      },
      "category":"DeFi",
      "issues": {
        "high": 1,
        "medium": 1,
        "low": 1,
        "informational": 0
      }
    },
    {
      "id": 4,
      "logo": "/dashboard/company_logo/na_logo.svg",
      "pageLink":false,
      "name": "Artpad",
      "trusted":false,
      "audit": {
        "link": "https://github.com/Defimoonorg/Audit-Report/blob/main/Artpad_audit.pdf"
      },
      "ecosystem": {
        "name":"solana",
        "icon":""
      },
      "category":"DeFi",
      "issues": {
        "high": 1,
        "medium": 1,
        "low": 1,
        "informational": 0
      }
    },
    {
      "id": 5,
      "logo": "public/tria.png",
      "pageLink":false,
      "name": "APAPAP",
      "trusted":false,
      "audit": {
        "link": "https://github.com/Defimoonorg/Audit-Report/blob/main/Artpad_audit.pdf"
      },
      "ecosystem": {
        "name":"solana",
        "icon":""
      },
      "category":"DeFi",
      "issues": {
        "high": 1,
        "medium": 1,
        "low": 1,
        "informational": 0
      }
    }
  ]
}
 